blomp_api/__init__.py
blomp_api/blomp.py
blomp_api/fso/__init__.py
blomp_api/fso/file.py
blomp_api/fso/folder.py
blomp_api/response_types/__init__.py
blomp_api/response_types/folder_data.py
blomp_api/response_types/share_link_response.py
blomp_api/utils/__init__.py
blomp_api/utils/path.py
blomp_api/utils/session.py
blomp_api/utils/user_agent.py
blomp_api/utils/monitor/__init__.py
blomp_api/utils/monitor/download_monitor.py
blomp_api/utils/monitor/monitor.py
blomp_api/utils/monitor/upload_monitor.py
blomp_api-1.0.4.dist-info/LICENSE
blomp_api-1.0.4.dist-info/METADATA
blomp_api-1.0.4.dist-info/WHEEL
blomp_api-1.0.4.dist-info/top_level.txt
blomp_api-1.0.4.dist-info/RECORD
