Metadata-Version: 2.1
Name: blomp-api
Version: 1.0.4
Summary: A unofficial Python API client to the Blomp cloud.
Home-page: https://pypi.org/project/blomp-api
Author: Izak76
License: MIT
Project-URL: Documentation, https://github.com/Izak76/blomp-api/blob/main/README.md
Project-URL: Source Code, https://github.com/Izak76/blomp-api
Project-URL: Bug Reports, https://github.com/Izak76/blomp-api/issues
Project-URL: Changes, https://github.com/Izak76/blomp-api/blob/main/CHANGELOG
Keywords: Python,Web API,Blomp,REST
Classifier: Development Status :: 4 - Beta
Classifier: Environment :: Web Environment
Classifier: Intended Audience :: Developers
Classifier: License :: OSI Approved :: MIT License
Classifier: Operating System :: OS Independent
Classifier: Programming Language :: Python :: 3
Classifier: Programming Language :: Python :: 3 :: Only
Classifier: Programming Language :: Python :: 3.8
Classifier: Programming Language :: Python :: 3.9
Classifier: Programming Language :: Python :: 3.10
Classifier: Programming Language :: Python :: 3.11
Classifier: Programming Language :: Python :: 3.12
Classifier: Topic :: Internet
Classifier: Topic :: Software Development :: Libraries :: Python Modules
Requires-Python: >=3.8
License-File: LICENSE
Requires-Dist: requests
Requires-Dist: requests-toolbelt
